del_fem_numpy-0.1.9.dist-info/METADATA
del_fem_numpy-0.1.9.dist-info/WHEEL
del_fem_numpy/Arap.py
del_fem_numpy/BlockSparse.py
del_fem_numpy/LaplacianMatrix.py
del_fem_numpy/LinearSolid.py
del_fem_numpy/MassMatrix.py
del_fem_numpy/Mitc3.py
del_fem_numpy/Rod3Darboux.py
del_fem_numpy/__init__.py
del_fem_numpy/del_fem_numpy.cpython-310-x86_64-linux-gnu.so
del_fem_numpy-0.1.9.dist-info/RECORD
