Metadata-Version: 2.4
Name: del-fem-numpy
Version: 0.1.9
Classifier: Programming Language :: Rust
Classifier: Programming Language :: Python :: Implementation :: CPython
Classifier: Programming Language :: Python :: Implementation :: PyPy
Requires-Dist: numpy
Requires-Dist: scipy
Requires-Dist: del-msh-numpy
Requires-Python: >=3.7
